README.txt
setup.py
xmpp_logging_handler/__init__.py
xmpp_logging_handler/emitter.py
xmpp_logging_handler.egg-info/PKG-INFO
xmpp_logging_handler.egg-info/SOURCES.txt
xmpp_logging_handler.egg-info/dependency_links.txt
xmpp_logging_handler.egg-info/requires.txt
xmpp_logging_handler.egg-info/top_level.txt