Metadata-Version: 1.0
Name: xmpp-logging-handler
Version: 1.0.2
Summary: A python logging framework handler sending to an xmpp server
Home-page: http://www.thisislevelup.com/
Author: Raymond McGinlay
Author-email: Raymond McGinlay
License: GPL v3 or higher
Platform: UNKNOWN
